ujjwal_phone_number_validator/__init__.py
ujjwal_phone_number_validator/validator.py
ujjwal_phone_number_validator-1.0.0.dist-info/METADATA
ujjwal_phone_number_validator-1.0.0.dist-info/WHEEL
ujjwal_phone_number_validator-1.0.0.dist-info/RECORD
